sapporo/__init__.py
sapporo/app.py
sapporo/auth.py
sapporo/auth_config.json
sapporo/cli.py
sapporo/config.py
sapporo/database.py
sapporo/exceptions.py
sapporo/executable_workflows.json
sapporo/factory.py
sapporo/ga4gh-wes-spec-1.1.0.yml
sapporo/ro_crate.py
sapporo/routers.py
sapporo/run.py
sapporo/run.sh
sapporo/schemas.py
sapporo/service_info.json
sapporo/utils.py
sapporo/validator.py
sapporo-2.1.0.dist-info/licenses/LICENSE
sapporo-2.1.0.dist-info/METADATA
sapporo-2.1.0.dist-info/WHEEL
sapporo-2.1.0.dist-info/entry_points.txt
sapporo-2.1.0.dist-info/top_level.txt
sapporo-2.1.0.dist-info/RECORD
