Metadata-Version: 2.4
Name: sapporo
Version: 2.1.0
Summary: The sapporo-service is a standard implementation conforming to the Global Alliance for Genomics and Health (GA4GH) Workflow Execution Service (WES) API specification.
Author-email: "DDBJ (Bioinfomatics and DDBJ Center)" <tazro.ohta@chiba-u.jp>
License: Apache-2.0
Project-URL: Homepage, https://github.com/sapporo-wes/sapporo-service
Project-URL: Documentation, https://github.com/sapporo-wes/sapporo-service/blob/main/README.md
Project-URL: Repository, https://github.com/sapporo-wes/sapporo-service.git
Keywords: workflow,WES,GA4GH-WES,bioinformatics
Classifier: Development Status :: 5 - Production/Stable
Classifier: Intended Audience :: Developers
Classifier: Intended Audience :: Science/Research
Classifier: License :: OSI Approved :: Apache Software License
Classifier: Programming Language :: Python :: 3
Classifier: Programming Language :: Python :: 3.8
Classifier: Programming Language :: Python :: 3.9
Classifier: Programming Language :: Python :: 3.10
Classifier: Programming Language :: Python :: 3.11
Classifier: Programming Language :: Python :: 3.12
Classifier: Topic :: Scientific/Engineering :: Bio-Informatics
Requires-Python: >=3.8
License-File: LICENSE
Requires-Dist: apscheduler
Requires-Dist: argon2-cffi
Requires-Dist: fastapi
Requires-Dist: httpx
Requires-Dist: multiqc
Requires-Dist: pydantic
Requires-Dist: pyjwt[crypto]
Requires-Dist: python-magic
Requires-Dist: python-multipart
Requires-Dist: pyyaml
Requires-Dist: rocrate
Requires-Dist: sqlmodel
Requires-Dist: uvicorn[standard]
Provides-Extra: tests
Requires-Dist: isort; extra == "tests"
Requires-Dist: mypy; extra == "tests"
Requires-Dist: pylint; extra == "tests"
Requires-Dist: pytest-cov; extra == "tests"
Requires-Dist: pytest-mock; extra == "tests"
Requires-Dist: pytest; extra == "tests"
Requires-Dist: types-PyYAML; extra == "tests"
Dynamic: license-file
